{
  "nodes": [
    {
      "id": "busd",
      "name": "BUSD",
      "value": 17651702084.31,
      "level": 0,
      "min-max": 0.40823620167292424,
      "z-score": 1.0715489832442955
    },
    {
      "id": "lily-pad",
      "name": "Lily Pad",
      "value": 46962.74,
      "level": 0,
      "min-max": 0.0000010833689830581159,
      "z-score": -0.421770963281307
    },
    {
      "id": "paxg",
      "name": "PAX Gold",
      "value": 613215423.36,
      "level": 0,
      "min-max": 0.014182014128023807,
      "z-score": -0.3698972615509051
    },
    {
      "id": "usdc",
      "name": "USD Coin",
      "value": 43238943390,
      "level": 0,
      "min-max": 1,
      "z-score": 3.2362149907768605
    },
    {
      "id": "usd",
      "name": "U.S. dollar",
      "value": 17651702084.31,
      "level": 1,
      "min-max": 0.40823620167292424,
      "z-score": 1.0715489832442955
    },
    {
      "id": "toad-network",
      "name": "Toad Network",
      "value": 10060.43,
      "level": 1,
      "min-max": 2.2991819984347137e-7,
      "z-score": -0.4217740851956666
    },
    {
      "id": "bnb",
      "name": "BNB",
      "value": 9022.63,
      "level": 1,
      "min-max": 2.0591668820855858e-7,
      "z-score": -0.42177417299295417
    },
    {
      "id": "pxbsc",
      "name": "Paradox NFT",
      "value": 1260.92,
      "level": 1,
      "min-max": 2.6409294807307045e-8,
      "z-score": -0.4217748296291893
    },
    {
      "id": "catoshi",
      "name": "Catoshi",
      "value": 724.71,
      "level": 1,
      "min-max": 1.4008205431939362e-8,
      "z-score": -0.4217748749922492
    },
    {
      "id": "gallant",
      "name": "Gallant",
      "value": 247.2,
      "level": 1,
      "min-max": 2.9646885493153488e-9,
      "z-score": -0.4217749153893226
    },
    {
      "id": "hoge",
      "name": "Hoge Finance",
      "value": 273.77,
      "level": 1,
      "min-max": 3.5791809025044336e-9,
      "z-score": -0.4217749131415157
    },
    {
      "id": "ethereum",
      "name": "Ethereum",
      "value": 218.52,
      "level": 1,
      "min-max": 2.301397593746551e-9,
      "z-score": -0.4217749178156342
    },
    {
      "id": "bitcoin",
      "name": "Bitcoin",
      "value": 197.48,
      "level": 1,
      "min-max": 1.814799207931784e-9,
      "z-score": -0.42177491959560626
    },
    {
      "id": "fukarens",
      "name": "FuckYouKarens",
      "value": 241.21,
      "level": 1,
      "min-max": 2.826156024076259e-9,
      "z-score": -0.4217749158960732
    },
    {
      "id": "bullishjackpot",
      "name": "Bullish Jackpot",
      "value": 119.01,
      "level": 1,
      "min-max": 0,
      "z-score": -0.4217749262341234
    },
    {
      "id": "gold",
      "name": "Gold",
      "value": 613215423.36,
      "level": 1,
      "min-max": 0.014182014128023807,
      "z-score": -0.3698972615509051
    }
  ],
  "links": [
    {
      "source": "busd",
      "target": "usd",
      "value": 17651702084.31,
      "level": 0,
      "min-max": 0.40823620167292424,
      "z-score": 1.1543575161050375
    },
    {
      "source": "lily-pad",
      "target": "toad-network",
      "value": 10060.43,
      "level": 0,
      "min-max": 2.2991819984347137e-7,
      "z-score": -0.3492730359821669
    },
    {
      "source": "lily-pad",
      "target": "bnb",
      "value": 9022.63,
      "level": 0,
      "min-max": 2.0591668820855858e-7,
      "z-score": -0.3492731243854647
    },
    {
      "source": "lily-pad",
      "target": "busd",
      "value": 6010.77,
      "level": 0,
      "min-max": 1.3626049931597004e-7,
      "z-score": -0.34927338094583915
    },
    {
      "source": "lily-pad",
      "target": "pxbsc",
      "value": 1260.92,
      "level": 0,
      "min-max": 2.6409294807307045e-8,
      "z-score": -0.3492737855540528
    },
    {
      "source": "lily-pad",
      "target": "catoshi",
      "value": 724.71,
      "level": 0,
      "min-max": 1.4008205431939362e-8,
      "z-score": -0.34927383123022576
    },
    {
      "source": "lily-pad",
      "target": "gallant",
      "value": 247.2,
      "level": 0,
      "min-max": 2.9646885493153488e-9,
      "z-score": -0.3492738719061352
    },
    {
      "source": "lily-pad",
      "target": "hoge",
      "value": 273.77,
      "level": 0,
      "min-max": 3.5791809025044336e-9,
      "z-score": -0.3492738696428131
    },
    {
      "source": "lily-pad",
      "target": "ethereum",
      "value": 218.52,
      "level": 0,
      "min-max": 2.301397593746551e-9,
      "z-score": -0.3492738743491941
    },
    {
      "source": "lily-pad",
      "target": "bitcoin",
      "value": 197.48,
      "level": 0,
      "min-max": 1.814799207931784e-9,
      "z-score": -0.34927387614145217
    },
    {
      "source": "lily-pad",
      "target": "fukarens",
      "value": 241.21,
      "level": 0,
      "min-max": 2.826156024076259e-9,
      "z-score": -0.3492738724163835
    },
    {
      "source": "lily-pad",
      "target": "bullishjackpot",
      "value": 119.01,
      "level": 0,
      "min-max": 0,
      "z-score": -0.3492738828257909
    },
    {
      "source": "lily-pad",
      "target": "usdc",
      "value": 580.95,
      "level": 0,
      "min-max": 1.0683424826201204e-8,
      "z-score": -0.34927384347618656
    },
    {
      "source": "paxg",
      "target": "gold",
      "value": 613215423.36,
      "level": 0,
      "min-max": 0.014182014128023807,
      "z-score": -0.29703813877469804
    },
    {
      "source": "usdc",
      "target": "usd",
      "value": 43238943390,
      "level": 0,
      "min-max": 1,
      "z-score": 3.3339648715253647
    }
  ]
}