{
    "history": [
        {
            "assets": {
                "usdt-tether-ethereum": 36982616.008051
            },
            "source": "https://eth-mainnet.g.alchemy.com/v2/{ALCHEMY_ETHEREUM}",
            "timestamp": "2023-04-15T23:43:05.379Z"
        },
        {
            "assets": {
                "usdt-tether-ethereum": 37522649.742444
            },
            "source": "https://eth-mainnet.g.alchemy.com/v2/{ALCHEMY_ETHEREUM}",
            "timestamp": "2023-04-16T17:10:04.463Z"
        },
        {
            "assets": {
                "usdt-tether-ethereum": 37976750.386445
            },
            "source": "https://eth-mainnet.g.alchemy.com/v2/{ALCHEMY_ETHEREUM}",
            "timestamp": "2023-04-17T05:11:19.796Z"
        },
        {
            "assets": {
                "usdt-tether-ethereum": 44726703.649818
            },
            "source": "https://eth-mainnet.g.alchemy.com/v2/{ALCHEMY_ETHEREUM}",
            "timestamp": "2023-04-17T17:10:37.640Z"
        },
        {
            "assets": {
                "usdt-tether-ethereum": 46040720.530785
            },
            "source": "https://eth-mainnet.g.alchemy.com/v2/{ALCHEMY_ETHEREUM}",
            "timestamp": "2023-04-18T05:10:55.325Z"
        },
        {
            "assets": {
                "usdt-tether-ethereum": 49984814.525239
            },
            "source": "https://eth-mainnet.g.alchemy.com/v2/{ALCHEMY_ETHEREUM}",
            "timestamp": "2023-04-18T17:09:25.475Z"
        },
        {
            "assets": {
                "usdt-tether-ethereum": 50412933.721204
            },
            "source": "https://eth-mainnet.g.alchemy.com/v2/{ALCHEMY_ETHEREUM}",
            "timestamp": "2023-04-18T22:00:10.814Z"
        },
        {
            "assets": {
                "usdt-tether-ethereum": 50412933.721204
            },
            "source": "https://eth-mainnet.g.alchemy.com/v2/{ALCHEMY_ETHEREUM}",
            "timestamp": "2023-04-18T22:45:39.988Z"
        },
        {
            "assets": {
                "usdt-tether-ethereum": 50114728.397783
            },
            "source": "https://eth-mainnet.g.alchemy.com/v2/{ALCHEMY_ETHEREUM}",
            "timestamp": "2023-04-19T05:11:10.003Z"
        },
        {
            "assets": {
                "usdt-tether-ethereum": 55327005.2415
            },
            "source": "https://eth-mainnet.g.alchemy.com/v2/{ALCHEMY_ETHEREUM}",
            "timestamp": "2023-04-19T17:10:24.351Z"
        },
        {
            "assets": {
                "usdt-tether-ethereum": 55389963.817534
            },
            "source": "https://eth-mainnet.g.alchemy.com/v2/{ALCHEMY_ETHEREUM}",
            "timestamp": "2023-04-20T05:12:19.129Z"
        },
        {
            "assets": {
                "usdt-tether-ethereum": 53824060.140483
            },
            "source": "https://eth-mainnet.g.alchemy.com/v2/{ALCHEMY_ETHEREUM}",
            "timestamp": "2023-04-20T17:11:01.313Z"
        },
        {
            "assets": {
                "usdt-tether-ethereum": 54869032.989324
            },
            "source": "https://eth-mainnet.g.alchemy.com/v2/{ALCHEMY_ETHEREUM}",
            "timestamp": "2023-04-21T05:11:06.416Z"
        },
        {
            "assets": {
                "usdt-tether-ethereum": 53243759.062376
            },
            "source": "https://eth-mainnet.g.alchemy.com/v2/{ALCHEMY_ETHEREUM}",
            "timestamp": "2023-04-21T17:10:58.243Z"
        },
        {
            "assets": {
                "usdt-tether-ethereum": 79473677.148739
            },
            "source": "https://eth-mainnet.g.alchemy.com/v2/{ALCHEMY_ETHEREUM}",
            "timestamp": "2023-04-22T05:11:18.276Z"
        },
        {
            "assets": {
                "usdt-tether-ethereum": 79512411.967323
            },
            "source": "https://eth-mainnet.g.alchemy.com/v2/{ALCHEMY_ETHEREUM}",
            "timestamp": "2023-04-22T17:10:37.993Z"
        },
        {
            "assets": {
                "usdt-tether-ethereum": 79518118.06185
            },
            "source": "https://eth-mainnet.g.alchemy.com/v2/{ALCHEMY_ETHEREUM}",
            "timestamp": "2023-04-23T05:12:29.629Z"
        },
        {
            "assets": {
                "usdt-tether-ethereum": 79199009.784225
            },
            "source": "https://eth-mainnet.g.alchemy.com/v2/{ALCHEMY_ETHEREUM}",
            "timestamp": "2023-04-23T17:10:53.733Z"
        },
        {
            "assets": {
                "usdt-tether-ethereum": 51459672.611717
            },
            "source": "https://eth-mainnet.g.alchemy.com/v2/{ALCHEMY_ETHEREUM}",
            "timestamp": "2023-04-24T05:12:24.966Z"
        },
        {
            "assets": {
                "usdt-tether-ethereum": 47623236.571717
            },
            "source": "https://eth-mainnet.g.alchemy.com/v2/{ALCHEMY_ETHEREUM}",
            "timestamp": "2023-04-24T17:10:56.739Z"
        }
    ]
}