{
	"tags": [
		{
			"id": "stock",
			"name": "Stock",
			"group": "asset-class"
		},
		{
			"id": "bond",
			"name": "Bond",
			"group": "asset-class"
		},
		{
			"id": "commodity",
			"name": "Commodity",
			"group": "asset-class"
		},
		{
			"id": "cryptocurrency",
			"name": "Cryptocurrency",
			"group": "asset-class"
		},
		{
			"id": "fiat",
			"name": "Fiat",
			"group": "asset-class"
		},
		{
			"id": "real-estate",
			"name": "Real estate",
			"group": "asset-class"
		},
		{
			"id": "infrastructure",
			"name": "Infrastructure",
			"group": "asset-class"
		},
		{
			"id": "vault",
			"name": "Vault",
			"group": "tech"
		},
		{
			"id": "stable",
			"name": "Stablecoin",
			"group": "tech"
		}
	],
	"groups": [
		{
			"id": "asset-class",
			"name": "Asset Class"
		},
		{
			"id": "tech",
			"name": "Technology"
		}
	]
}
