{
  "timestamp": "2023-02-12T22:10:20.280Z",
  "nodes": [
    {
      "id": "unbacked",
      "value": 48207.52
    },
    {
      "id": "hoge-multichain-bsc",
      "name": "Hoge Finance",
      "value": 445593.56,
      "level": 0
    },
    {
      "id": "hoge-ethereum",
      "name": "Hoge Finance",
      "value": 397386.04,
      "level": 1
    }
  ],
  "links": [
    {
      "source": "hoge-multichain-bsc",
      "target": "unbacked",
      "value": 48207.52,
      "level": 0
    },
    {
      "source": "hoge-multichain-bsc",
      "target": "hoge-ethereum",
      "value": 397386.04,
      "level": 0
    },
    {
      "source": "hoge-ethereum",
      "target": "unbacked",
      "value": 397386.04,
      "level": 1
    }
  ],
  "value": 445593.56,
  "unbacked": 48207.52,
  "backed": 397386.04
}