{
  "timestamp": "2023-02-26T22:09:12.410Z",
  "nodes": [
    {
      "id": "lp-hoge-toad-toad.network-bsc",
      "name": "HOGE-TOAD LPs",
      "value": 20222.94,
      "level": 0
    },
    {
      "id": "unbacked",
      "value": 0
    },
    {
      "id": "hoge-multichain-bsc",
      "name": "Hoge Finance",
      "value": 10321.24,
      "level": 1
    },
    {
      "id": "hoge-ethereum",
      "name": "Hoge Finance",
      "value": 10321.24,
      "level": 2
    },
    {
      "id": "toad-toad.network-bsc",
      "name": "Toad Network",
      "value": 9901.7,
      "level": 1
    }
  ],
  "links": [
    {
      "source": "lp-hoge-toad-toad.network-bsc",
      "target": "hoge-multichain-bsc",
      "value": 10321.24,
      "level": 0
    },
    {
      "source": "hoge-multichain-bsc",
      "target": "hoge-ethereum",
      "value": 10321.24,
      "level": 1
    },
    {
      "source": "hoge-ethereum",
      "target": "unbacked",
      "value": 10321.24,
      "level": 2
    },
    {
      "source": "lp-hoge-toad-toad.network-bsc",
      "target": "toad-toad.network-bsc",
      "value": 9901.7,
      "level": 0
    },
    {
      "source": "toad-toad.network-bsc",
      "target": "unbacked",
      "value": 9901.7,
      "level": 1
    }
  ],
  "value": 20222.94,
  "unbacked": 0,
  "backed": 20222.94
}