{
    "aave": {
        "id": "aave",
        "name": "Aave",
        "reference": "https://aave.com/",
        "tags": [],
        "git": {
            "updated": {
                "hash": "70d552756e6ac4be466655a444352451338dfa68",
                "date": "2023-04-18T19:48:46.000Z"
            },
            "created": {
                "hash": "70d552756e6ac4be466655a444352451338dfa68",
                "date": "2023-04-18T19:48:46.000Z"
            }
        }
    },
    "abracadabra": {
        "id": "abracadabra",
        "name": "Abracadabra",
        "reference": "https://abracadabra.money/",
        "tags": [],
        "git": {
            "updated": {
                "hash": "b6ace21e67dc716e4297bfca4fcc4752f2843b5d",
                "date": "2023-05-19T14:46:55.000Z"
            },
            "created": {
                "hash": "b6ace21e67dc716e4297bfca4fcc4752f2843b5d",
                "date": "2023-05-19T14:46:55.000Z"
            }
        }
    },
    "allbridge": {
        "id": "allbridge",
        "name": "Allbridge",
        "reference": "https://allbridge.io/",
        "tags": [
            "bridge"
        ],
        "git": {
            "updated": {
                "hash": "582a44205d2389f913b46607a06868928a502c0d",
                "date": "2023-01-31T21:59:44.000Z"
            },
            "created": {
                "hash": "582a44205d2389f913b46607a06868928a502c0d",
                "date": "2023-01-31T21:59:44.000Z"
            }
        }
    },
    "binance": {
        "id": "binance",
        "name": "Binance",
        "reference": "https://www.binance.com/",
        "tags": [
            "cex"
        ],
        "git": {
            "updated": {
                "hash": "582a44205d2389f913b46607a06868928a502c0d",
                "date": "2023-01-31T21:59:44.000Z"
            },
            "created": {
                "hash": "582a44205d2389f913b46607a06868928a502c0d",
                "date": "2023-01-31T21:59:44.000Z"
            }
        }
    },
    "catoshi": {
        "id": "catoshi",
        "name": "Catoshi",
        "reference": "https://www.catoshi.tech/",
        "tags": [
            "bridge"
        ],
        "git": {
            "updated": {
                "hash": "582a44205d2389f913b46607a06868928a502c0d",
                "date": "2023-01-31T21:59:44.000Z"
            },
            "created": {
                "hash": "582a44205d2389f913b46607a06868928a502c0d",
                "date": "2023-01-31T21:59:44.000Z"
            }
        }
    },
    "circle": {
        "id": "circle",
        "name": "Circle",
        "reference": "https://www.circle.com/",
        "tags": [],
        "git": {
            "updated": {
                "hash": "582a44205d2389f913b46607a06868928a502c0d",
                "date": "2023-01-31T21:59:44.000Z"
            },
            "created": {
                "hash": "582a44205d2389f913b46607a06868928a502c0d",
                "date": "2023-01-31T21:59:44.000Z"
            }
        }
    },
    "compound": {
        "id": "compound",
        "name": "Compound Labs",
        "reference": "https://compound.finance/",
        "tags": [],
        "git": {
            "updated": {
                "hash": "a2573df4ac1ad4b7b03e2b53ebb3aa714a16e7d4",
                "date": "2023-04-15T23:16:30.000Z"
            },
            "created": {
                "hash": "a2573df4ac1ad4b7b03e2b53ebb3aa714a16e7d4",
                "date": "2023-04-15T23:16:30.000Z"
            }
        }
    },
    "convex": {
        "id": "convex",
        "name": "Convex Finance",
        "reference": "https://www.convexfinance.com/",
        "tags": [],
        "git": {
            "updated": {
                "hash": "7d79d22473ffe188d6a0813a47bb9e06dc5e5f05",
                "date": "2023-05-19T20:58:30.000Z"
            },
            "created": {
                "hash": "7d79d22473ffe188d6a0813a47bb9e06dc5e5f05",
                "date": "2023-05-19T20:58:30.000Z"
            }
        }
    },
    "curve": {
        "id": "curve",
        "name": "Curve",
        "reference": "https://curve.fi/",
        "tags": [],
        "git": {
            "updated": {
                "hash": "b6ace21e67dc716e4297bfca4fcc4752f2843b5d",
                "date": "2023-05-19T14:46:55.000Z"
            },
            "created": {
                "hash": "b6ace21e67dc716e4297bfca4fcc4752f2843b5d",
                "date": "2023-05-19T14:46:55.000Z"
            }
        }
    },
    "ethereumfoundation": {
        "id": "ethereumfoundation",
        "name": "ethereum foundation",
        "reference": "https://ethereum.foundation/",
        "tags": [
            "chain"
        ],
        "git": {
            "updated": {
                "hash": "04fc04eb635cb3ad0be13567b30c2bb48d2b8574",
                "date": "2023-03-25T22:23:10.000Z"
            },
            "created": {
                "hash": "04fc04eb635cb3ad0be13567b30c2bb48d2b8574",
                "date": "2023-03-25T22:23:10.000Z"
            }
        }
    },
    "fed": {
        "id": "fed",
        "name": "Federal Reserve",
        "reference": "https://www.federalreserve.gov/",
        "tags": [
            "central bank"
        ],
        "git": {
            "updated": {
                "hash": "582a44205d2389f913b46607a06868928a502c0d",
                "date": "2023-01-31T21:59:44.000Z"
            },
            "created": {
                "hash": "582a44205d2389f913b46607a06868928a502c0d",
                "date": "2023-01-31T21:59:44.000Z"
            }
        }
    },
    "flux": {
        "id": "flux",
        "name": "Flux Finance",
        "reference": "https://fluxfinance.com/",
        "tags": [],
        "git": {
            "updated": {
                "hash": "b6ace21e67dc716e4297bfca4fcc4752f2843b5d",
                "date": "2023-05-19T14:46:55.000Z"
            },
            "created": {
                "hash": "b6ace21e67dc716e4297bfca4fcc4752f2843b5d",
                "date": "2023-05-19T14:46:55.000Z"
            }
        }
    },
    "frax": {
        "id": "frax",
        "name": "Frax Finance",
        "reference": "https://frax.finance/",
        "tags": [],
        "git": {
            "updated": {
                "hash": "bb62fb1a893663b8c97037ade88a236f142cca92",
                "date": "2023-05-24T20:42:07.000Z"
            },
            "created": {
                "hash": "b6ace21e67dc716e4297bfca4fcc4752f2843b5d",
                "date": "2023-05-19T14:46:55.000Z"
            }
        }
    },
    "lido": {
        "id": "lido",
        "name": "Lido",
        "reference": "https://lido.fi/",
        "tags": [],
        "git": {
            "updated": {
                "hash": "ac75fcde188bc2ad4870acbf36d976f8c7a1cc71",
                "date": "2023-05-14T14:58:40.000Z"
            },
            "created": {
                "hash": "ac75fcde188bc2ad4870acbf36d976f8c7a1cc71",
                "date": "2023-05-14T14:58:40.000Z"
            }
        }
    },
    "maker": {
        "id": "maker",
        "name": "MakerDAO",
        "reference": "https://makerdao.com/",
        "tags": [],
        "git": {
            "updated": {
                "hash": "b6ace21e67dc716e4297bfca4fcc4752f2843b5d",
                "date": "2023-05-19T14:46:55.000Z"
            },
            "created": {
                "hash": "b6ace21e67dc716e4297bfca4fcc4752f2843b5d",
                "date": "2023-05-19T14:46:55.000Z"
            }
        }
    },
    "mobilecoin": {
        "id": "mobilecoin",
        "name": "MobileCoin",
        "reference": "https://mobilecoin.com/",
        "tags": [],
        "git": {
            "updated": {
                "hash": "3d3bd2c5cdcada77d94bb3bf7b6978ff2bd91bb6",
                "date": "2023-04-18T20:13:30.000Z"
            },
            "created": {
                "hash": "3d3bd2c5cdcada77d94bb3bf7b6978ff2bd91bb6",
                "date": "2023-04-18T20:13:30.000Z"
            }
        }
    },
    "moonbeamfoundation": {
        "id": "moonbeamfoundation",
        "name": "Moonbeam Foundation",
        "reference": "https://moonbeam.foundation/",
        "tags": [
            "chain"
        ],
        "git": {
            "updated": {
                "hash": "73cce3e3cc4a45681b2dd644feb6e4712bc24d61",
                "date": "2023-03-25T22:43:37.000Z"
            },
            "created": {
                "hash": "73cce3e3cc4a45681b2dd644feb6e4712bc24d61",
                "date": "2023-03-25T22:43:37.000Z"
            }
        }
    },
    "multichain": {
        "id": "multichain",
        "name": "Multichain",
        "reference": "https://multichain.org/",
        "tags": [
            "bridge"
        ],
        "git": {
            "updated": {
                "hash": "582a44205d2389f913b46607a06868928a502c0d",
                "date": "2023-01-31T21:59:44.000Z"
            },
            "created": {
                "hash": "582a44205d2389f913b46607a06868928a502c0d",
                "date": "2023-01-31T21:59:44.000Z"
            }
        }
    },
    "paxos": {
        "id": "paxos",
        "name": "Paxos",
        "reference": "https://paxos.com/",
        "tags": [],
        "git": {
            "updated": {
                "hash": "582a44205d2389f913b46607a06868928a502c0d",
                "date": "2023-01-31T21:59:44.000Z"
            },
            "created": {
                "hash": "582a44205d2389f913b46607a06868928a502c0d",
                "date": "2023-01-31T21:59:44.000Z"
            }
        }
    },
    "reserve": {
        "id": "reserve",
        "name": "Reserve",
        "reference": "https://reserve.org/",
        "tags": [],
        "git": {
            "updated": {
                "hash": "a2573df4ac1ad4b7b03e2b53ebb3aa714a16e7d4",
                "date": "2023-04-15T23:16:30.000Z"
            },
            "created": {
                "hash": "a2573df4ac1ad4b7b03e2b53ebb3aa714a16e7d4",
                "date": "2023-04-15T23:16:30.000Z"
            }
        }
    },
    "rocketpool": {
        "id": "rocketpool",
        "name": "Rocket Pool",
        "reference": "https://rocketpool.net/",
        "tags": [],
        "git": {
            "updated": {
                "hash": "ac75fcde188bc2ad4870acbf36d976f8c7a1cc71",
                "date": "2023-05-14T14:58:40.000Z"
            },
            "created": {
                "hash": "ac75fcde188bc2ad4870acbf36d976f8c7a1cc71",
                "date": "2023-05-14T14:58:40.000Z"
            }
        }
    },
    "solanafoundation": {
        "id": "solanafoundation",
        "name": "Solana Foundation",
        "reference": "https://solana.org/",
        "tags": [
            "chain"
        ],
        "git": {
            "updated": {
                "hash": "be842b8ad7a0454dc31ed87ddab23b61b84279d2",
                "date": "2023-03-25T21:49:36.000Z"
            },
            "created": {
                "hash": "be842b8ad7a0454dc31ed87ddab23b61b84279d2",
                "date": "2023-03-25T21:49:36.000Z"
            }
        }
    },
    "tether": {
        "id": "tether",
        "name": "Tether",
        "reference": "https://tether.to/",
        "tags": [],
        "git": {
            "updated": {
                "hash": "a2573df4ac1ad4b7b03e2b53ebb3aa714a16e7d4",
                "date": "2023-04-15T23:16:30.000Z"
            },
            "created": {
                "hash": "a2573df4ac1ad4b7b03e2b53ebb3aa714a16e7d4",
                "date": "2023-04-15T23:16:30.000Z"
            }
        }
    },
    "toadnetwork": {
        "id": "toadnetwork",
        "name": "Toad.Network",
        "reference": "https://toad.network/",
        "tags": [
            "dex"
        ],
        "git": {
            "updated": {
                "hash": "c424329d3baa96d8b6d09f217a465ad136ac4826",
                "date": "2023-03-25T22:02:37.000Z"
            },
            "created": {
                "hash": "582a44205d2389f913b46607a06868928a502c0d",
                "date": "2023-01-31T21:59:44.000Z"
            }
        }
    },
    "wormhole": {
        "id": "wormhole",
        "name": "Wormhole",
        "reference": "https://wormhole.com/",
        "tags": [
            "bridge"
        ],
        "git": {
            "updated": {
                "hash": "582a44205d2389f913b46607a06868928a502c0d",
                "date": "2023-01-31T21:59:44.000Z"
            },
            "created": {
                "hash": "582a44205d2389f913b46607a06868928a502c0d",
                "date": "2023-01-31T21:59:44.000Z"
            }
        }
    }
}