{
    "history": [
        {
            "timestamp": "2022-06-11T00:00:00.000Z",
            "total": 195000,
            "source": "https://bscscan.com/token/0x463e737d8f740395abf44f7aac2d9531d8d539e9"
        },
        {
            "timestamp": "2023-02-02T20:58:58.063Z",
            "total": 200000,
            "source": "https://bsc-dataseed3.binance.org/"
        },
        {
            "timestamp": "2023-02-03T19:17:12.681Z",
            "total": 200000,
            "source": "https://bsc-dataseed3.binance.org/"
        },
        {
            "timestamp": "2023-02-03T22:09:21.454Z",
            "total": 200000,
            "source": "https://bsc-dataseed3.binance.org/"
        },
        {
            "timestamp": "2023-02-04T22:09:01.640Z",
            "total": 200000,
            "source": "https://bsc-dataseed3.binance.org/"
        },
        {
            "timestamp": "2023-02-05T12:18:56.500Z",
            "total": 200000,
            "source": "https://bsc-dataseed3.binance.org/"
        },
        {
            "timestamp": "2023-02-06T17:03:48.687Z",
            "total": 200000,
            "source": "https://bsc-dataseed3.binance.org/"
        },
        {
            "timestamp": "2023-02-07T22:10:54.225Z",
            "total": 200000,
            "source": "https://bsc-dataseed3.binance.org/"
        },
        {
            "timestamp": "2023-02-08T22:11:03.209Z",
            "total": 200000,
            "source": "https://bsc-dataseed3.binance.org/"
        },
        {
            "timestamp": "2023-02-12T22:10:21.222Z",
            "total": 200000,
            "source": "https://bsc-dataseed3.binance.org/"
        },
        {
            "timestamp": "2023-02-14T22:10:39.092Z",
            "total": 200000,
            "source": "https://bsc-dataseed3.binance.org/"
        },
        {
            "timestamp": "2023-02-19T11:47:02.173Z",
            "total": 200000,
            "source": "https://bsc-dataseed3.binance.org/"
        },
        {
            "timestamp": "2023-02-20T22:09:33.594Z",
            "total": 200000,
            "source": "https://bsc-dataseed3.binance.org/"
        },
        {
            "timestamp": "2023-02-21T22:09:51.821Z",
            "total": 200000,
            "source": "https://bsc-dataseed3.binance.org/"
        },
        {
            "timestamp": "2023-02-22T22:08:52.369Z",
            "total": 200000,
            "source": "https://bsc-dataseed3.binance.org/"
        },
        {
            "timestamp": "2023-02-23T22:10:13.120Z",
            "total": 200000,
            "source": "https://bsc-dataseed3.binance.org/"
        },
        {
            "timestamp": "2023-02-24T22:09:47.388Z",
            "total": 200000,
            "source": "https://bsc-dataseed3.binance.org/"
        },
        {
            "timestamp": "2023-02-25T22:09:26.503Z",
            "total": 200000,
            "source": "https://bsc-dataseed3.binance.org/"
        },
        {
            "timestamp": "2023-02-26T22:09:12.409Z",
            "total": 200000,
            "source": "https://bsc-dataseed3.binance.org/"
        },
        {
            "timestamp": "2023-02-27T22:10:30.547Z",
            "total": 200000,
            "source": "https://bsc-dataseed3.binance.org/"
        },
        {
            "timestamp": "2023-02-28T22:10:14.765Z",
            "total": 200000,
            "source": "https://bsc-dataseed3.binance.org/"
        },
        {
            "timestamp": "2023-03-01T22:09:43.346Z",
            "total": 200000,
            "source": "https://bsc-dataseed3.binance.org/"
        },
        {
            "timestamp": "2023-03-02T22:09:02.957Z",
            "total": 200000,
            "source": "https://bsc-dataseed3.binance.org/"
        },
        {
            "timestamp": "2023-03-03T22:09:56.625Z",
            "total": 200000,
            "source": "https://bsc-dataseed3.binance.org/"
        },
        {
            "timestamp": "2023-03-04T22:09:14.391Z",
            "total": 200000,
            "source": "https://bsc-dataseed3.binance.org/"
        },
        {
            "total": 200000,
            "timestamp": "2023-03-05T17:13:31.073Z",
            "source": "https://bsc-dataseed3.binance.org/"
        },
        {
            "total": 200000,
            "timestamp": "2023-03-05T22:10:09.094Z",
            "source": "https://bsc-dataseed3.binance.org/"
        },
        {
            "total": 200000,
            "timestamp": "2023-03-06T22:10:47.165Z",
            "source": "https://bsc-dataseed3.binance.org/"
        },
        {
            "total": 200000,
            "timestamp": "2023-03-07T18:22:09.560Z",
            "source": "https://bsc-dataseed3.binance.org/"
        },
        {
            "total": 200000,
            "timestamp": "2023-03-07T20:12:44.462Z",
            "source": "https://bsc-dataseed3.binance.org/"
        },
        {
            "total": 200000,
            "timestamp": "2023-03-09T22:10:29.708Z",
            "source": "https://bsc-dataseed3.binance.org/"
        },
        {
            "total": 200000,
            "timestamp": "2023-03-10T22:09:26.970Z",
            "source": "https://bsc-dataseed3.binance.org/"
        },
        {
            "total": 200000,
            "timestamp": "2023-03-11T14:36:23.310Z",
            "source": "https://bsc-dataseed3.binance.org/"
        },
        {
            "total": 200000,
            "timestamp": "2023-03-12T21:45:02.083Z",
            "source": "https://bsc-dataseed3.binance.org/"
        },
        {
            "total": 200000,
            "timestamp": "2023-03-13T22:10:44.723Z",
            "source": "https://bsc-dataseed3.binance.org/"
        },
        {
            "total": 200000,
            "timestamp": "2023-03-14T22:10:15.209Z",
            "source": "https://bsc-dataseed3.binance.org/"
        },
        {
            "total": 200000,
            "timestamp": "2023-03-15T22:10:42.409Z",
            "source": "https://bsc-dataseed3.binance.org/"
        },
        {
            "total": 200000,
            "timestamp": "2023-03-16T22:10:34.333Z",
            "source": "https://bsc-dataseed3.binance.org/"
        },
        {
            "total": 200000,
            "timestamp": "2023-03-17T22:10:08.276Z",
            "source": "https://bsc-dataseed3.binance.org/"
        },
        {
            "total": 200000,
            "timestamp": "2023-03-18T22:09:33.512Z",
            "source": "https://bsc-dataseed3.binance.org/"
        },
        {
            "total": 200000,
            "timestamp": "2023-03-19T17:11:50.245Z",
            "source": "https://bsc-dataseed3.binance.org/"
        },
        {
            "total": 200000,
            "timestamp": "2023-03-20T19:21:53.816Z",
            "source": "https://bsc-dataseed3.binance.org/"
        },
        {
            "total": 200000,
            "timestamp": "2023-03-21T22:13:11.697Z",
            "source": "https://bsc-dataseed3.binance.org/"
        },
        {
            "total": 200000,
            "timestamp": "2023-03-22T17:11:22.137Z",
            "source": "https://bsc-dataseed3.binance.org/"
        },
        {
            "total": 200000,
            "timestamp": "2023-03-23T20:16:31.132Z",
            "source": "https://bsc-dataseed3.binance.org/"
        },
        {
            "total": 200000,
            "timestamp": "2023-03-24T22:10:22.260Z",
            "source": "https://bsc-dataseed3.binance.org/"
        },
        {
            "total": 200000,
            "timestamp": "2023-03-25T16:17:26.833Z",
            "source": "https://bsc-dataseed3.binance.org/"
        },
        {
            "total": 200000,
            "timestamp": "2023-03-26T15:54:15.321Z",
            "source": "https://bsc-dataseed3.binance.org/"
        },
        {
            "total": 200000,
            "timestamp": "2023-03-27T19:27:51.358Z",
            "source": "https://bsc-dataseed3.binance.org/"
        },
        {
            "total": 200000,
            "timestamp": "2023-03-28T22:10:44.503Z",
            "source": "https://bsc-dataseed3.binance.org/"
        },
        {
            "total": 200000,
            "timestamp": "2023-03-29T22:11:09.940Z",
            "source": "https://bsc-dataseed3.binance.org/"
        },
        {
            "total": 200000,
            "timestamp": "2023-03-30T18:23:40.459Z",
            "source": "https://bsc-dataseed3.binance.org/"
        },
        {
            "total": 200000,
            "timestamp": "2023-03-31T21:52:41.954Z",
            "source": "https://bsc-dataseed3.binance.org/"
        },
        {
            "total": 200000,
            "timestamp": "2023-04-01T22:10:28.858Z",
            "source": "https://bsc-dataseed3.binance.org/"
        },
        {
            "total": 200000,
            "timestamp": "2023-04-02T22:09:42.377Z",
            "source": "https://bsc-dataseed3.binance.org/"
        },
        {
            "total": 200000,
            "timestamp": "2023-04-03T19:29:38.850Z",
            "source": "https://bsc-dataseed3.binance.org/"
        },
        {
            "total": 200000,
            "timestamp": "2023-04-04T22:10:39.632Z",
            "source": "https://bsc-dataseed3.binance.org/"
        },
        {
            "total": 200000,
            "timestamp": "2023-04-05T22:10:15.985Z",
            "source": "https://bsc-dataseed3.binance.org/"
        },
        {
            "total": 200000,
            "timestamp": "2023-04-06T20:59:59.158Z",
            "source": "https://bsc-dataseed3.binance.org/"
        },
        {
            "total": 200000,
            "timestamp": "2023-04-07T22:10:42.250Z",
            "source": "https://bsc-dataseed3.binance.org/"
        },
        {
            "total": 200000,
            "timestamp": "2023-04-08T22:10:31.808Z",
            "source": "https://bsc-dataseed3.binance.org/"
        },
        {
            "total": 200000,
            "timestamp": "2023-04-09T22:10:50.570Z",
            "source": "https://bsc-dataseed3.binance.org/"
        },
        {
            "total": 200000,
            "timestamp": "2023-04-10T22:11:18.029Z",
            "source": "https://bsc-dataseed3.binance.org/"
        },
        {
            "total": 200000,
            "timestamp": "2023-04-11T22:11:07.378Z",
            "source": "https://bsc-dataseed3.binance.org/"
        },
        {
            "total": 200000,
            "timestamp": "2023-04-12T22:11:14.744Z",
            "source": "https://bsc-dataseed3.binance.org/"
        },
        {
            "total": 200000,
            "timestamp": "2023-04-13T22:11:09.132Z",
            "source": "https://bsc-dataseed3.binance.org/"
        },
        {
            "total": 200000,
            "timestamp": "2023-04-14T22:11:12.133Z",
            "source": "https://bsc-dataseed3.binance.org/"
        },
        {
            "total": 200000,
            "timestamp": "2023-04-15T22:11:08.929Z",
            "source": "https://bsc-dataseed3.binance.org/"
        },
        {
            "total": 200000,
            "timestamp": "2023-04-15T23:43:06.312Z",
            "source": "https://bsc-dataseed3.binance.org/"
        },
        {
            "total": 200000,
            "timestamp": "2023-04-16T17:10:04.531Z",
            "source": "https://bsc-dataseed3.binance.org/"
        },
        {
            "total": 200000,
            "timestamp": "2023-04-17T05:11:20.052Z",
            "source": "https://bsc-dataseed3.binance.org/"
        },
        {
            "total": 200000,
            "timestamp": "2023-04-17T17:10:37.875Z",
            "source": "https://bsc-dataseed3.binance.org/"
        },
        {
            "total": 200000,
            "timestamp": "2023-04-18T05:10:55.666Z",
            "source": "https://bsc-dataseed3.binance.org/"
        },
        {
            "total": 200000,
            "timestamp": "2023-04-18T17:09:25.810Z",
            "source": "https://bsc-dataseed3.binance.org/"
        },
        {
            "total": 200000,
            "timestamp": "2023-04-18T22:00:10.917Z",
            "source": "https://bsc-dataseed3.binance.org/"
        },
        {
            "total": 200000,
            "timestamp": "2023-04-18T22:45:40.877Z",
            "source": "https://bsc-dataseed3.binance.org/"
        },
        {
            "total": 200000,
            "timestamp": "2023-04-19T05:11:10.635Z",
            "source": "https://bsc-dataseed3.binance.org/"
        },
        {
            "total": 200000,
            "timestamp": "2023-04-19T17:10:25.359Z",
            "source": "https://bsc-dataseed3.binance.org/"
        },
        {
            "total": 200000,
            "timestamp": "2023-04-20T05:12:19.939Z",
            "source": "https://bsc-dataseed3.binance.org/"
        },
        {
            "total": 200000,
            "timestamp": "2023-04-20T17:11:02.030Z",
            "source": "https://bsc-dataseed3.binance.org/"
        },
        {
            "total": 200000,
            "timestamp": "2023-04-21T05:11:06.715Z",
            "source": "https://bsc-dataseed3.binance.org/"
        }
    ]
}